fastapi_xray/__init__.py
fastapi_xray/cli.py
fastapi_xray/schemas.py
fastapi_xray/xray.py
fastapi_xray/commons/__init__.py
fastapi_xray/commons/logger/__init__.py
fastapi_xray/server/__init__.py
fastapi_xray/server/receiver.py
fastapi_xray/ui/__init__.py
fastapi_xray/ui/app.py
fastapi_xray/ui/main.css
fastapi_xray/ui/components/__init__.py
fastapi_xray/ui/components/panel_factory.py
fastapi_xray/ui/components/panels.py
fastapi_xray/ui/components/widgets/__init__.py
fastapi_xray/ui/components/widgets/list.py
fastapi_xray/ui/components/widgets/panels.py
fastapi_xray/ui/components/widgets/text.py
fastapi_xray-0.1.1.dist-info/METADATA
fastapi_xray-0.1.1.dist-info/WHEEL
fastapi_xray-0.1.1.dist-info/entry_points.txt
fastapi_xray-0.1.1.dist-info/top_level.txt
fastapi_xray-0.1.1.dist-info/RECORD
