Metadata-Version: 2.1
Name: fastapi-xray
Version: 0.1.1
Summary: A FastAPI debug tool to look into request/response
Author-email: Ropali Munshi <ropali68@example.com>
Classifier: Programming Language :: Python :: 3
Classifier: License :: OSI Approved :: MIT License
Classifier: Operating System :: OS Independent
Requires-Python: >=3.8
Requires-Dist: setuptools (~=66.1.1)
Requires-Dist: typer (~=0.7.0)
Requires-Dist: fastapi (~=0.95.1)
Requires-Dist: textual (~=0.22.3)
Requires-Dist: rich (~=13.3.5)
Requires-Dist: pydantic (~=1.10.7)
